ImtiazGermain/__init__.py
ImtiazGermain/primecheck.py
ImtiazGermain-0.1.1.dist-info/LICENSE
ImtiazGermain-0.1.1.dist-info/METADATA
ImtiazGermain-0.1.1.dist-info/WHEEL
ImtiazGermain-0.1.1.dist-info/top_level.txt
ImtiazGermain-0.1.1.dist-info/RECORD
