Metadata-Version: 2.1
Name: ImtiazGermain
Version: 0.1.1
Summary: A Python library for checking if a number is a Imtiaz-Germain and Germain prime or not
Home-page: https://ImtiazGermain.readthedocs.io/
Author: Aitzaz Imtiaz
Author-email: aitzazimtiaz855@gmail.com
Classifier: Development Status :: 3 - Alpha
Classifier: Programming Language :: Python :: 3
Classifier: License :: OSI Approved :: MIT License
Classifier: Operating System :: OS Independent
Requires-Python: >=3.6
License-File: LICENSE
Requires-Dist: sympy
